exe_analyzer_mcp/__init__.py
exe_analyzer_mcp/analysis_orchestrator.py
exe_analyzer_mcp/cli.py
exe_analyzer_mcp/framework_detector.py
exe_analyzer_mcp/language_inferrer.py
exe_analyzer_mcp/library_analyzer.py
exe_analyzer_mcp/mcp_server.py
exe_analyzer_mcp/pe_parser.py
exe_analyzer_mcp/string_extractor.py
exe_analyzer_mcp/config/__init__.py
exe_analyzer_mcp/config/compiler_signatures.json
exe_analyzer_mcp/config/framework_signatures.json
exe_analyzer_mcp/config/system_libraries.json
exe_analyzer_mcp-0.1.0.dist-info/METADATA
exe_analyzer_mcp-0.1.0.dist-info/WHEEL
exe_analyzer_mcp-0.1.0.dist-info/entry_points.txt
exe_analyzer_mcp-0.1.0.dist-info/RECORD
