Metadata-Version: 2.4
Name: exe-analyzer-mcp
Version: 0.1.0
Summary: MCP server for automated analysis of Windows executable files
Requires-Python: >=3.12
Requires-Dist: hypothesis>=6.0.0
Requires-Dist: mcp>=1.0.0
Requires-Dist: pefile>=2023.2.7
Requires-Dist: pytest>=8.0.0
Provides-Extra: dev
Requires-Dist: ruff>=0.14.8; extra == 'dev'
